provisio/__init__.py
provisio/provisio.py
provisio/provisio_exceptions.py
provisio/provision_logic.py
provisio/utils.py
provisio-0.1.7.dist-info/METADATA
provisio-0.1.7.dist-info/WHEEL
provisio-0.1.7.dist-info/RECORD
