Metadata-Version: 2.1
Name: provisio
Version: 0.1.7
Summary: Small utility library containing city provision metric used in other projects
Author: Danila
Author-email: 63115678+DDonnyy@users.noreply.github.com
Requires-Python: >=3.9,<4.0
Classifier: Programming Language :: Python :: 3
Classifier: Programming Language :: Python :: 3.9
Classifier: Programming Language :: Python :: 3.10
Classifier: Programming Language :: Python :: 3.11
Classifier: Programming Language :: Python :: 3.12
Requires-Dist: geopandas (>=0.14.3,<0.15.0)
Requires-Dist: loguru (>=0.7.2,<0.8.0)
Requires-Dist: momepy (>=0.6.0,<0.7.0)
Requires-Dist: networkit (>=11.0,<12.0)
Requires-Dist: networkx (>=3.2.1,<4.0.0)
Requires-Dist: numpy (>=1.23.5,<2.0.0)
Requires-Dist: osm2geojson (>=0.2.5,<0.3.0)
Requires-Dist: osmnx (>=1.9.2,<2.0.0)
Requires-Dist: pandas (>=2.2.0,<3.0.0)
Requires-Dist: pulp (>=2.8.0,<3.0.0)
Requires-Dist: pydantic (>=2.6.1,<3.0.0)
Requires-Dist: tqdm (>=4.66.2,<5.0.0)
